FlaskBB-2.0.2.dist-info/METADATA
FlaskBB-2.0.2.dist-info/RECORD
FlaskBB-2.0.2.dist-info/WHEEL
FlaskBB-2.0.2.dist-info/entry_points.txt
FlaskBB-2.0.2.dist-info/top_level.txt
flaskbb/__init__.py
flaskbb/_compat.py
flaskbb/app.py
flaskbb/email.py
flaskbb/exceptions.py
flaskbb/extensions.py
flaskbb/markup.py
flaskbb/auth/__init__.py
flaskbb/auth/forms.py
flaskbb/auth/plugins.py
flaskbb/auth/views.py
flaskbb/auth/services/__init__.py
flaskbb/auth/services/activation.py
flaskbb/auth/services/authentication.py
flaskbb/auth/services/factories.py
flaskbb/auth/services/password.py
flaskbb/auth/services/reauthentication.py
flaskbb/auth/services/registration.py
flaskbb/cli/__init__.py
flaskbb/cli/main.py
flaskbb/cli/plugins.py
flaskbb/cli/themes.py
flaskbb/cli/translations.py
flaskbb/cli/users.py
flaskbb/cli/utils.py
flaskbb/configs/__init__.py
flaskbb/configs/config.cfg.template
flaskbb/configs/default.py
flaskbb/configs/testing.py
flaskbb/core/__init__.py
flaskbb/core/exceptions.py
flaskbb/core/tokens.py
flaskbb/core/auth/__init__.py
flaskbb/core/auth/activation.py
flaskbb/core/auth/authentication.py
flaskbb/core/auth/password.py
flaskbb/core/auth/registration.py
flaskbb/core/user/__init__.py
flaskbb/core/user/repo.py
flaskbb/fixtures/__init__.py
flaskbb/fixtures/groups.py
flaskbb/fixtures/settings.py
flaskbb/forum/__init__.py
flaskbb/forum/forms.py
flaskbb/forum/locals.py
flaskbb/forum/models.py
flaskbb/forum/views.py
flaskbb/management/__init__.py
flaskbb/management/forms.py
flaskbb/management/models.py
flaskbb/management/plugins.py
flaskbb/management/views.py
flaskbb/plugins/__init__.py
flaskbb/plugins/manager.py
flaskbb/plugins/models.py
flaskbb/plugins/spec.py
flaskbb/plugins/utils.py
flaskbb/static/.gitkeep
flaskbb/static/favicon.ico
flaskbb/static/robots.txt
flaskbb/static/css/pygments.css
flaskbb/static/css/styles.css
flaskbb/static/fonts/FontAwesome.otf
flaskbb/static/fonts/fontawesome-webfont.eot
flaskbb/static/fonts/fontawesome-webfont.svg
flaskbb/static/fonts/fontawesome-webfont.ttf
flaskbb/static/fonts/fontawesome-webfont.woff
