Metadata-Version: 2.1
Name: FlaskBB
Version: 2.0.2
Summary: A classic Forum Software in Python using Flask.
Home-page: https://flaskbb.org
Author: Peter Justin
Author-email: peter.justin@outlook.com
License: BSD
Project-URL: Code, https://github.com/flaskbb/flaskbb
Project-URL: Issue Tracker, https://github.com/flaskbb/flaskbb
Project-URL: Documentation, https://flaskbb.readthedocs.io/en/latest/
Platform: any
Classifier: Development Status :: 4 - Beta
Classifier: Environment :: Web Environment
Classifier: Intended Audience :: Developers
Classifier: Intended Audience :: End Users/Desktop
Classifier: License :: OSI Approved :: BSD License
Classifier: Operating System :: OS Independent
Classifier: Programming Language :: Python
Classifier: Programming Language :: Python :: 3
Classifier: Topic :: Internet :: WWW/HTTP :: Dynamic Content
Classifier: Topic :: Software Development :: Libraries :: Python Modules
Requires-Python: >=2.7,!=3.0.*,!=3.1.*,!=3.2.*,!=3.3.*
Requires-Dist: alembic (==0.9.9)
Requires-Dist: amqp (==2.1.4)
Requires-Dist: attrs (==17.4.0)
Requires-Dist: Babel (==2.5.3)
Requires-Dist: billiard (==3.5.0.2)
Requires-Dist: blinker (==1.4)
Requires-Dist: celery (==4.0.2)
Requires-Dist: certifi (==2018.4.16)
Requires-Dist: chardet (==3.0.4)
Requires-Dist: click (==6.7)
Requires-Dist: click-log (==0.2.1)
Requires-Dist: enum34 (==1.1.6)
Requires-Dist: Flask (==1.0.2)
Requires-Dist: Flask-Alembic (==2.0.1)
Requires-Dist: flask-allows (==0.4.0)
Requires-Dist: Flask-BabelPlus (==2.1.1)
Requires-Dist: Flask-Caching (==1.4.0)
Requires-Dist: Flask-DebugToolbar (==0.10.1)
Requires-Dist: Flask-Limiter (==1.0.1)
Requires-Dist: Flask-Login (==0.4.1)
Requires-Dist: Flask-Mail (==0.9.1)
Requires-Dist: Flask-Redis (==0.3.0)
Requires-Dist: Flask-SQLAlchemy (==2.3.2)
Requires-Dist: Flask-Themes2 (==0.1.4)
Requires-Dist: flask-whooshee (==0.5.0)
Requires-Dist: Flask-WTF (==0.14.2)
Requires-Dist: flaskbb-plugin-conversations (==1.0.2)
Requires-Dist: flaskbb-plugin-portal (==1.1.1)
Requires-Dist: idna (==2.6)
Requires-Dist: itsdangerous (==0.24)
Requires-Dist: Jinja2 (==2.10)
Requires-Dist: kombu (==4.0.2)
Requires-Dist: limits (==1.3)
Requires-Dist: Mako (==1.0.7)
Requires-Dist: MarkupSafe (==1.0)
Requires-Dist: mistune (==0.8.3)
Requires-Dist: olefile (==0.45.1)
Requires-Dist: Pillow (==5.1.0)
Requires-Dist: pluggy (==0.6.0)
Requires-Dist: Pygments (==2.2.0)
Requires-Dist: python-dateutil (==2.7.2)
Requires-Dist: python-editor (==1.0.3)
Requires-Dist: pytz (==2018.4)
Requires-Dist: redis (==2.10.6)
Requires-Dist: requests (==2.18.4)
Requires-Dist: simplejson (==3.14.0)
Requires-Dist: six (==1.11.0)
Requires-Dist: speaklater (==1.3)
Requires-Dist: SQLAlchemy (==1.2.7)
Requires-Dist: SQLAlchemy-Utils (==0.33.3)
Requires-Dist: Unidecode (==1.0.22)
Requires-Dist: urllib3 (==1.22)
Requires-Dist: vine (==1.1.4)
Requires-Dist: Werkzeug (==0.14.1)
Requires-Dist: Whoosh (==2.7.4)
Requires-Dist: WTForms (==2.1)
